tdsr/__init__.py
tdsr/cli.py
tdsr/config.py
tdsr/constants.py
tdsr/exceptions.py
tdsr/plotting.py
tdsr/tdsr.py
tdsr/types.py
tdsr/utils.py
tdsr/version.py
tdsr/loading/__init__.py
tdsr/loading/background.py
tdsr/loading/custom.py
tdsr/loading/cyclic.py
tdsr/loading/four_point.py
tdsr/loading/loading.py
tdsr/loading/ramp.py
tdsr/loading/step.py
tdsr/loading/trend_change.py
tdsr-0.0.8.dist-info/AUTHORS.rst
tdsr-0.0.8.dist-info/COPYING
tdsr-0.0.8.dist-info/LICENSE
tdsr-0.0.8.dist-info/METADATA
tdsr-0.0.8.dist-info/WHEEL
tdsr-0.0.8.dist-info/entry_points.txt
tdsr-0.0.8.dist-info/top_level.txt
tdsr-0.0.8.dist-info/RECORD
