Metadata-Version: 2.1
Name: tdsr
Version: 0.0.8
Summary: tdsr
Home-page: https://github.com/torstendahm/tdsr
Author: torstendahm
Author-email: torsten.dahm@gfz-potsdam.de
License: GPLv3
Keywords: tdsr
Classifier: Development Status :: 5 - Production/Stable
Classifier: Intended Audience :: Developers
Classifier: Intended Audience :: Education
Classifier: Intended Audience :: Science/Research
Classifier: License :: OSI Approved :: GNU General Public License v3 (GPLv3)
Classifier: Environment :: Console
Classifier: Natural Language :: English
Classifier: Programming Language :: Python
Classifier: Programming Language :: Python :: 3 :: Only
Classifier: Operating System :: POSIX
Classifier: Operating System :: MacOS
Classifier: Topic :: Scientific/Engineering
Classifier: Topic :: Scientific/Engineering :: Physics
Requires-Python: >=3.7
License-File: LICENSE
License-File: COPYING
License-File: AUTHORS.rst
Requires-Dist: click
Requires-Dist: numpy
Requires-Dist: toml
Provides-Extra: dev
Requires-Dist: click ; extra == 'dev'
Requires-Dist: numpy ; extra == 'dev'
Requires-Dist: toml ; extra == 'dev'
Requires-Dist: tox ; extra == 'dev'
Requires-Dist: pytest ; extra == 'dev'
Requires-Dist: pytest-cov ; extra == 'dev'
Requires-Dist: pytest-xdist ; extra == 'dev'
Requires-Dist: pytest-sugar ; extra == 'dev'
Requires-Dist: mypy ; extra == 'dev'
Requires-Dist: pyfakefs ; extra == 'dev'
Requires-Dist: pytest-subtests ; extra == 'dev'
Requires-Dist: types-setuptools ; extra == 'dev'
Requires-Dist: flake8 ; extra == 'dev'
Requires-Dist: black ; extra == 'dev'
Requires-Dist: isort ; extra == 'dev'
Requires-Dist: invoke ; extra == 'dev'
Requires-Dist: pre-commit ; extra == 'dev'
Requires-Dist: bump2version ; extra == 'dev'
Provides-Extra: test
Requires-Dist: tox ; extra == 'test'
Requires-Dist: pytest ; extra == 'test'
Requires-Dist: pytest-cov ; extra == 'test'
Requires-Dist: pytest-xdist ; extra == 'test'
Requires-Dist: pytest-sugar ; extra == 'test'
Requires-Dist: mypy ; extra == 'test'
Requires-Dist: pyfakefs ; extra == 'test'
Requires-Dist: pytest-subtests ; extra == 'test'
Requires-Dist: types-setuptools ; extra == 'test'
